{
  "race_id": "202602010607",
  "date": "2026-06-28",
  "track": "函館",
  "race_no": 7,
  "race_name": "3歳以上1勝クラス",
  "distance_m": 1700,
  "surface": "ダート",
  "going": "稍重",
  "updated_at": "2026-07-02T23:21:38+09:00",
  "market_overround": 1.26,
  "value_note": "隠れ複勝候補: 10番。 妙味のある馬 1頭（EV≧1.0）。",
  "hidden_picks": [
    10
  ],
  "horses": [
    {
      "umaban": 1,
      "name": "ウィンターガーデン",
      "horse_id": "2021105857",
      "sex_age": "牝5",
      "jockey": "☆舟山",
      "trainer": "栗東井上",
      "weight_carried": 55.0,
      "horse_weight": "496(+2)",
      "odds_win": 34.1,
      "popularity": 7,
      "features": {
        "n_runs": 5,
        "best_agari": 37.7,
        "avg_agari": 38.28,
        "dist_surface_fit": 5,
        "days_since_last": 78,
        "style_ratio": 0.722,
        "style": "追込"
      },
      "form_score": -2.8504,
      "ability_prob": 0.0578,
      "ability_n_data": 22,
      "q_win": 0.0233,
      "p_win": 0.0107,
      "ev_win": 0.365,
      "edge": -0.0126,
      "mark": "",
      "reasons": [
        "実力+騎手スコア 5.8%・8番手評価",
        "7番人気 / EV 0.365（やや過剰人気・妙味なし）",
        "近走: 上がり最速37.7 / 追込 / 当条件近走5走（実力面はやや割引）"
      ]
    },
    {
      "umaban": 2,
      "name": "ビーチイン",
      "horse_id": "2023105830",
      "sex_age": "牝3",
      "jockey": "横山和",
      "trainer": "美浦和田勇",
      "weight_carried": 53.0,
      "horse_weight": "420(0)",
      "odds_win": 4.8,
      "popularity": 3,
      "features": {
        "n_runs": 5,
        "best_agari": 38.1,
        "avg_agari": 39.4,
        "dist_surface_fit": 5,
        "days_since_last": 15,
        "style_ratio": 0.341,
        "style": "差し"
      },
      "form_score": -1.8656,
      "ability_prob": 0.1548,
      "ability_n_data": 7,
      "q_win": 0.1654,
      "p_win": 0.1838,
      "ev_win": 0.882,
      "edge": 0.0184,
      "mark": "○",
      "reasons": [
        "実力+騎手スコア 15.5%・2番手評価",
        "3番人気 / EV 0.882（控除率の壁で理論上マイナス）",
        "近走: 上がり最速38.1 / 差し / 当条件近走5走（実力で上積み評価）"
      ]
    },
    {
      "umaban": 3,
      "name": "キタノサリスカ",
      "horse_id": "2023105977",
      "sex_age": "牝3",
      "jockey": "▲和田陽",
      "trainer": "栗東羽月",
      "weight_carried": 50.0,
      "horse_weight": "430(+4)",
      "odds_win": 43.7,
      "popularity": 8,
      "features": {
        "n_runs": 4,
        "best_agari": 37.5,
        "avg_agari": 38.8,
        "dist_surface_fit": 2,
        "days_since_last": 71,
        "style_ratio": 0.563,
        "style": "差し"
      },
      "form_score": -3.4246,
      "ability_prob": 0.0326,
      "ability_n_data": 4,
      "q_win": 0.0182,
      "p_win": 0.0057,
      "ev_win": 0.249,
      "edge": -0.0125,
      "mark": "",
      "reasons": [
        "実力+騎手スコア 3.3%・10番手評価",
        "8番人気 / EV 0.249（やや過剰人気・妙味なし）",
        "近走: 上がり最速37.5 / 差し / 当条件近走2走（実力面はやや割引）"
      ]
    },
    {
      "umaban": 4,
      "name": "キャットテイル",
      "horse_id": "2022101678",
      "sex_age": "牝4",
      "jockey": "★河原田",
      "trainer": "栗東野中",
      "weight_carried": 52.0,
      "horse_weight": "424(+2)",
      "odds_win": 6.7,
      "popularity": 4,
      "features": {
        "n_runs": 5,
        "best_agari": 37.4,
        "avg_agari": 38.06,
        "dist_surface_fit": 3,
        "days_since_last": 35,
        "style_ratio": 0.113,
        "style": "逃げ・先行"
      },
      "form_score": -2.5088,
      "ability_prob": 0.0814,
      "ability_n_data": 9,
      "q_win": 0.1185,
      "p_win": 0.0852,
      "ev_win": 0.571,
      "edge": -0.0333,
      "mark": "",
      "reasons": [
        "実力+騎手スコア 8.1%・6番手評価",
        "4番人気 / EV 0.571（やや過剰人気・妙味なし）",
        "近走: 上がり最速37.4 / 逃げ・先行 / 当条件近走3走"
      ]
    },
    {
      "umaban": 5,
      "name": "アリストクラシア",
      "horse_id": "2021105238",
      "sex_age": "牝5",
      "jockey": "岩田望",
      "trainer": "栗東吉岡",
      "weight_carried": 56.0,
      "horse_weight": "484(+2)",
      "odds_win": 3.4,
      "popularity": 1,
      "features": {
        "n_runs": 5,
        "best_agari": 36.2,
        "avg_agari": 37.16,
        "dist_surface_fit": 5,
        "days_since_last": 57,
        "style_ratio": 0.613,
        "style": "差し"
      },
      "form_score": -2.3071,
      "ability_prob": 0.0996,
      "ability_n_data": 16,
      "q_win": 0.2335,
      "p_win": 0.2097,
      "ev_win": 0.713,
      "edge": -0.0238,
      "mark": "△",
      "reasons": [
        "実力+騎手スコア 10.0%・4番手評価",
        "1番人気 / EV 0.713（やや過剰人気・妙味なし）",
        "近走: 上がり最速36.2 / 差し / 当条件近走5走（実力で上積み評価）"
      ]
    },
    {
      "umaban": 6,
      "name": "ガーネットフレア",
      "horse_id": "2023107075",
      "sex_age": "牝3",
      "jockey": "鮫島駿",
      "trainer": "栗東杉山佳",
      "weight_carried": 53.0,
      "horse_weight": "450(-2)",
      "odds_win": 6.8,
      "popularity": 5,
      "features": {
        "n_runs": 4,
        "best_agari": 38.8,
        "avg_agari": 39.1,
        "dist_surface_fit": 3,
        "days_since_last": 14,
        "style_ratio": 0.301,
        "style": "逃げ・先行"
      },
      "form_score": -2.6512,
      "ability_prob": 0.0706,
      "ability_n_data": 6,
      "q_win": 0.1167,
      "p_win": 0.0768,
      "ev_win": 0.522,
      "edge": -0.0399,
      "mark": "",
      "reasons": [
        "実力+騎手スコア 7.1%・7番手評価",
        "5番人気 / EV 0.522（やや過剰人気・妙味なし）",
        "近走: 上がり最速38.8 / 逃げ・先行 / 当条件近走3走（実力面はやや割引）"
      ]
    },
    {
      "umaban": 7,
      "name": "ヒミノエトワール",
      "horse_id": "2022102388",
      "sex_age": "牝4",
      "jockey": "武豊",
      "trainer": "栗東宮地",
      "weight_carried": 56.0,
      "horse_weight": "470(0)",
      "odds_win": 3.5,
      "popularity": 2,
      "features": {
        "n_runs": 5,
        "best_agari": 36.4,
        "avg_agari": 37.36,
        "dist_surface_fit": 0,
        "days_since_last": 50,
        "style_ratio": 0.35,
        "style": "差し"
      },
      "form_score": -1.3458,
      "ability_prob": 0.2603,
      "ability_n_data": 11,
      "q_win": 0.2268,
      "p_win": 0.361,
      "ev_win": 1.264,
      "edge": 0.1342,
      "mark": "◎",
      "reasons": [
        "実力+騎手スコア 26.0%・1番手評価",
        "2番人気 / EV 1.264（理論上プラス＝妙味 +13.4pt）",
        "近走: 上がり最速36.4 / 差し（実力で上積み評価）"
      ]
    },
    {
      "umaban": 8,
      "name": "サウンドルーチェ",
      "horse_id": "2022105267",
      "sex_age": "牝4",
      "jockey": "▲小林美",
      "trainer": "栗東渡辺",
      "weight_carried": 53.0,
      "horse_weight": "456(0)",
      "odds_win": 10.6,
      "popularity": 6,
      "features": {
        "n_runs": 4,
        "best_agari": 37.6,
        "avg_agari": 38.67,
        "dist_surface_fit": 3,
        "days_since_last": 105,
        "style_ratio": 0.242,
        "style": "逃げ・先行"
      },
      "form_score": -2.3254,
      "ability_prob": 0.0977,
      "ability_n_data": 13,
      "q_win": 0.0749,
      "p_win": 0.0561,
      "ev_win": 0.595,
      "edge": -0.0188,
      "mark": "",
      "reasons": [
        "実力+騎手スコア 9.8%・5番手評価",
        "6番人気 / EV 0.595（やや過剰人気・妙味なし）",
        "近走: 上がり最速37.6 / 逃げ・先行 / 当条件近走3走（実力で上積み評価）"
      ]
    },
    {
      "umaban": 9,
      "name": "ゴールドヴィーナス",
      "horse_id": "2023105672",
      "sex_age": "牝3",
      "jockey": "松本",
      "trainer": "栗東森秀",
      "weight_carried": 53.0,
      "horse_weight": "458(0)",
      "odds_win": 85.4,
      "popularity": 10,
      "features": {
        "n_runs": 5,
        "best_agari": 34.4,
        "avg_agari": 36.26,
        "dist_surface_fit": 0,
        "days_since_last": 14,
        "style_ratio": 0.357,
        "style": "差し"
      },
      "form_score": -3.2112,
      "ability_prob": 0.0403,
      "ability_n_data": 8,
      "q_win": 0.0093,
      "p_win": 0.003,
      "ev_win": 0.256,
      "edge": -0.0063,
      "mark": "",
      "reasons": [
        "実力+騎手スコア 4.0%・9番手評価",
        "10番人気 / EV 0.256（控除率の壁で理論上マイナス）",
        "近走: 上がり最速34.4 / 差し（実力面はやや割引）"
      ]
    },
    {
      "umaban": 10,
      "name": "シャンデヴィーニュ",
      "horse_id": "2023107384",
      "sex_age": "牝3",
      "jockey": "北村友",
      "trainer": "栗東柴田",
      "weight_carried": 53.0,
      "horse_weight": "446(+2)",
      "odds_win": 58.8,
      "popularity": 9,
      "features": {
        "n_runs": 5,
        "best_agari": 38.5,
        "avg_agari": 39.88,
        "dist_surface_fit": 2,
        "days_since_last": 71,
        "style_ratio": 0.203,
        "style": "逃げ・先行"
      },
      "form_score": -2.2544,
      "ability_prob": 0.1049,
      "ability_n_data": 7,
      "q_win": 0.0135,
      "p_win": 0.0082,
      "ev_win": 0.482,
      "edge": -0.0053,
      "mark": "▲",
      "reasons": [
        "実力+騎手スコア 10.5%・3番手評価",
        "9番人気 / EV 0.482（控除率の壁で理論上マイナス）",
        "近走: 上がり最速38.5 / 逃げ・先行 / 当条件近走2走（実力で上積み評価）",
        "隠れ複勝候補: 実力+騎手3番手評価なのに9番人気（市場の見落とし筋・検証で複勝率2倍超）"
      ],
      "hidden_pick": true
    }
  ],
  "tickets": [
    {
      "type": "単勝",
      "target": "7",
      "ev": 1.264,
      "stake_unit": 1,
      "note": "1番手評価・妙味 +13.4pt"
    }
  ]
}